bmdcluster/__init__.py
bmdcluster/initializers/__init__.py
bmdcluster/initializers/bootstrap_initializer.py
bmdcluster/initializers/cluster_initializers.py
bmdcluster/initializers/primary_initializer.py
bmdcluster/optimizers/__init__.py
bmdcluster/optimizers/blockdiagonalBMD.py
bmdcluster/optimizers/generalBMD.py
bmdcluster-0.3.1.dist-info/LICENSE
bmdcluster-0.3.1.dist-info/METADATA
bmdcluster-0.3.1.dist-info/WHEEL
bmdcluster-0.3.1.dist-info/top_level.txt
bmdcluster-0.3.1.dist-info/RECORD
