Metadata-Version: 2.1
Name: bmdcluster
Version: 0.3.1
Summary: Binary Matrix Decomposition algorithm for clustering binary data
Home-page: https://github.com/csprock/bmdcluster
Author: Carson Sprock
Author-email: csprock@gmail.com
License: MIT license
Keywords: bmdcluster
Platform: UNKNOWN
Classifier: Development Status :: 3 - Alpha
Classifier: Intended Audience :: Science/Research
Classifier: License :: OSI Approved :: MIT License
Classifier: Natural Language :: English
Classifier: Programming Language :: Python :: 3.4
Classifier: Programming Language :: Python :: 3.5
Classifier: Programming Language :: Python :: 3.6
Classifier: Programming Language :: Python :: 3.7
Requires-Dist: numpy (>=1.14)
